cli/__init__.py
cli/main.py
dencyy-0.1.0.dist-info/METADATA
dencyy-0.1.0.dist-info/WHEEL
dencyy-0.1.0.dist-info/entry_points.txt
dencyy-0.1.0.dist-info/top_level.txt
dencyy-0.1.0.dist-info/RECORD
